{"swagger":"2.0","info":{"title":"","description":"File upload and download","version":""},"host":"localhost:80","consumes":["application/json","application/xml","application/gob"],"produces":["application/json","application/xml","application/gob"],"paths":{"/":{"post":{"tags":["upload"],"summary":"upload upload","operationId":"upload#upload","consumes":["multipart/form-data"],"parameters":[{"name":"bytes","in":"formData","required":true,"schema":{"type":"string","format":"byte"}}],"responses":{"200":{"description":"OK response.","schema":{"type":"string"}}},"schemes":["http"]}},"/{id}":{"get":{"tags":["upload"],"summary":"download upload","operationId":"upload#download","parameters":[{"name":"id","in":"path","required":true,"type":"string"}],"responses":{"200":{"description":"OK response.","schema":{"type":"string","format":"byte"}}},"schemes":["http"]}}}}